README.md
setup.cfg
setup.py
elasticsearch_app/__init__.py
elasticsearch_app/apps.py
elasticsearch_app/search.py
elasticsearch_app/signals.py
elasticsearch_app/urls.py
elasticsearch_app/utils.py
elasticsearch_app/views.py
elasticsearch_app/management/__init__.py
elasticsearch_app/management/commands/__init__.py
elasticsearch_app/management/commands/clear_index.py
elasticsearch_app/management/commands/haystack_clear.py
elasticsearch_app/management/commands/rebuild_index.py
elasticsearch_app/management/commands/update_index.py
geonode_elasticsearch_app.egg-info/PKG-INFO
geonode_elasticsearch_app.egg-info/SOURCES.txt
geonode_elasticsearch_app.egg-info/dependency_links.txt
geonode_elasticsearch_app.egg-info/requires.txt
geonode_elasticsearch_app.egg-info/top_level.txt