Metadata-Version: 1.1
Name: geonode-elasticsearch-app
Version: 0.2.3
Summary: Elasticsearch app for indexing GeoNode models via elasticsearch-dsl
Home-page: https://github.com/boundlessgeo/geonode-elasticsearch
Author: tbrundage
Author-email: tbrundage@boundlessgeo.com
License: GPLv2
Platform: UNKNOWN
Classifier: Environment :: Web Environment
Classifier: Intended Audience :: Developers
Classifier: License :: OSI Approved :: GNU General Public License v2 (GPLv2)
Classifier: Operating System :: OS Independent
Classifier: Programming Language :: Python
Classifier: Framework :: Django
